fast_captcha-0.3.0.dist-info/METADATA
fast_captcha-0.3.0.dist-info/WHEEL
fast_captcha-0.3.0.dist-info/licenses/LICENSE
fast_captcha/__init__.py
fast_captcha/fonts/3Dumb.ttf
fast_captcha/fonts/ApothecaryFont.ttf
fast_captcha/fonts/BY-Easy-love-2.ttf
fast_captcha/fonts/D3Parallelism.ttf
fast_captcha/fonts/DENNEthree-dee.ttf
fast_captcha/fonts/Maler.ttf
fast_captcha/fonts/MoonRocks.ttf
fast_captcha/fonts/Shojumaru.ttf
fast_captcha/fonts/actionj.ttf
fast_captcha/img_captcha.py
fast_captcha/text_captcha.py
fast_captcha-0.3.0.dist-info/RECORD
