Metadata-Version: 2.1
Name: fast_captcha
Version: 0.3.0
Summary: Fast to use captcha
Home-page: https://github.com/wu-clan/fast_captcha
Author-Email: Wu Clan <jianhengwu0407@gmail.com>
License: MIT
Classifier: Intended Audience :: Developers
Classifier: License :: OSI Approved :: MIT License
Classifier: Operating System :: OS Independent
Classifier: Programming Language :: Python :: 3 :: Only
Classifier: Programming Language :: Python :: 3.8
Classifier: Programming Language :: Python :: 3.9
Classifier: Programming Language :: Python :: 3.10
Classifier: Programming Language :: Python :: 3.11
Classifier: Programming Language :: Python :: 3.12
Classifier: Topic :: Software Development :: Libraries
Classifier: Topic :: Software Development :: Libraries :: Python Modules
Project-URL: Homepage, https://github.com/wu-clan/fast_captcha
Project-URL: Repository, https://github.com/wu-clan/fast_captcha
Requires-Python: <4.0,>=3.8
Requires-Dist: Pillow>=10.0.0
